rplidar.py
rplidar_mrumel-1.1.2.dist-info/LICENSE
rplidar_mrumel-1.1.2.dist-info/METADATA
rplidar_mrumel-1.1.2.dist-info/WHEEL
rplidar_mrumel-1.1.2.dist-info/top_level.txt
rplidar_mrumel-1.1.2.dist-info/zip-safe
rplidar_mrumel-1.1.2.dist-info/RECORD
